{
  "updated_at_utc": "2026-05-22T20:00:10.975400+00:00",
  "source": {
    "deposit_url": "https://stg-risk.mcwchat.com/admin/dashboard-summary-deposit/filter",
    "withdrawal_url": "https://stg-risk.mcwchat.com/admin/dashboard-summary-withdrawal/filter"
  },
  "brands": {
    "M1": {
      "group": "MCW",
      "deposit_count": 35563.0,
      "deposit_amount": 51761116.94,
      "deposit_difference": 9700722.909999996,
      "deposit_date": "2026-05-23",
      "deposit_time": "04:00",
      "withdrawal_count": 11364.0,
      "withdrawal_amount": 46831061.02,
      "withdrawal_difference": 0.0,
      "withdrawal_date": "2026-05-23",
      "withdrawal_time": "05:00",
      "net_flow": 4930055.919999994,
      "withdrawal_pressure": 90.47536797609145
    },
    "B1": {
      "group": "MCW",
      "deposit_count": 9150.0,
      "deposit_amount": 9714196.0,
      "deposit_difference": 1745337.0,
      "deposit_date": "2026-05-23",
      "deposit_time": "04:00",
      "withdrawal_count": 2920.0,
      "withdrawal_amount": 8085608.14,
      "withdrawal_difference": 0.0,
      "withdrawal_date": "2026-05-23",
      "withdrawal_time": "05:00",
      "net_flow": 1628587.8600000003,
      "withdrawal_pressure": 83.23497014060659
    },
    "K1": {
      "group": "MCW",
      "deposit_count": 7767.0,
      "deposit_amount": 6790455.65,
      "deposit_difference": 1292823.0,
      "deposit_date": "2026-05-23",
      "deposit_time": "04:00",
      "withdrawal_count": 2339.0,
      "withdrawal_amount": 6531498.39,
      "withdrawal_difference": 1400557.0,
      "withdrawal_date": "2026-05-23",
      "withdrawal_time": "04:00",
      "net_flow": 258957.2600000007,
      "withdrawal_pressure": 96.18645237746306
    },
    "M2": {
      "group": "MCW",
      "deposit_count": 3217.0,
      "deposit_amount": 4778814.0,
      "deposit_difference": 856806.0,
      "deposit_date": "2026-05-23",
      "deposit_time": "04:00",
      "withdrawal_count": 1176.0,
      "withdrawal_amount": 4255265.6,
      "withdrawal_difference": 972083.9999999995,
      "withdrawal_date": "2026-05-23",
      "withdrawal_time": "04:00",
      "net_flow": 523548.4000000004,
      "withdrawal_pressure": 89.04438632681665
    },
    "B2": {
      "group": "MCW",
      "deposit_count": 3777.0,
      "deposit_amount": 3952340.0,
      "deposit_difference": 617097.0,
      "deposit_date": "2026-05-23",
      "deposit_time": "04:00",
      "withdrawal_count": 1278.0,
      "withdrawal_amount": 3841108.57,
      "withdrawal_difference": 1053716.3199999998,
      "withdrawal_date": "2026-05-23",
      "withdrawal_time": "04:00",
      "net_flow": 111231.43000000017,
      "withdrawal_pressure": 97.18568164682188
    },
    "B4": {
      "group": "MCW",
      "deposit_count": 1099.0,
      "deposit_amount": 1106793.0,
      "deposit_difference": 241997.0,
      "deposit_date": "2026-05-23",
      "deposit_time": "04:00",
      "withdrawal_count": 343.0,
      "withdrawal_amount": 1170525.0,
      "withdrawal_difference": 209000.0,
      "withdrawal_date": "2026-05-23",
      "withdrawal_time": "04:00",
      "net_flow": -63732.0,
      "withdrawal_pressure": 105.75825831930632
    },
    "B3": {
      "group": "MCW",
      "deposit_count": 795.0,
      "deposit_amount": 907451.0,
      "deposit_difference": 146970.0,
      "deposit_date": "2026-05-23",
      "deposit_time": "04:00",
      "withdrawal_count": 250.0,
      "withdrawal_amount": 1162721.0,
      "withdrawal_difference": 215529.0,
      "withdrawal_date": "2026-05-23",
      "withdrawal_time": "04:00",
      "net_flow": -255270.0,
      "withdrawal_pressure": 128.1304445088495
    },
    "TK": {
      "group": "MCW",
      "deposit_count": 547.0,
      "deposit_amount": 607993.0,
      "deposit_difference": 103490.0,
      "deposit_date": "2026-05-23",
      "deposit_time": "04:00",
      "withdrawal_count": 170.0,
      "withdrawal_amount": 481417.0,
      "withdrawal_difference": 112064.0,
      "withdrawal_date": "2026-05-23",
      "withdrawal_time": "04:00",
      "net_flow": 126576.0,
      "withdrawal_pressure": 79.18133925884015
    },
    "B5": {
      "group": "MCW",
      "deposit_count": 354.0,
      "deposit_amount": 284540.0,
      "deposit_difference": 61071.0,
      "deposit_date": "2026-05-23",
      "deposit_time": "04:00",
      "withdrawal_count": 93.0,
      "withdrawal_amount": 255427.0,
      "withdrawal_difference": 42686.0,
      "withdrawal_date": "2026-05-23",
      "withdrawal_time": "04:00",
      "net_flow": 29113.0,
      "withdrawal_pressure": 89.76839811625781
    },
    "JY": {
      "group": "MCW",
      "deposit_count": 298.0,
      "deposit_amount": 257602.0,
      "deposit_difference": 36068.0,
      "deposit_date": "2026-05-23",
      "deposit_time": "04:00",
      "withdrawal_count": 69.0,
      "withdrawal_amount": 185958.0,
      "withdrawal_difference": 18036.0,
      "withdrawal_date": "2026-05-23",
      "withdrawal_time": "04:00",
      "net_flow": 71644.0,
      "withdrawal_pressure": 72.18810412962632
    },
    "CX": {
      "group": "CX",
      "deposit_count": 30253.0,
      "deposit_amount": 48249614.08,
      "deposit_difference": 9507716.68,
      "deposit_date": "2026-05-23",
      "deposit_time": "04:00",
      "withdrawal_count": 11429.0,
      "withdrawal_amount": 46177999.71,
      "withdrawal_difference": 11272491.649999999,
      "withdrawal_date": "2026-05-23",
      "withdrawal_time": "04:00",
      "net_flow": 2071614.3699999973,
      "withdrawal_pressure": 95.70646437385972
    },
    "MB": {
      "group": "CX",
      "deposit_count": 17860.0,
      "deposit_amount": 26896853.72,
      "deposit_difference": 4821939.109999999,
      "deposit_date": "2026-05-23",
      "deposit_time": "04:00",
      "withdrawal_count": 7155.0,
      "withdrawal_amount": 27854624.46,
      "withdrawal_difference": 6501229.870000001,
      "withdrawal_date": "2026-05-23",
      "withdrawal_time": "04:00",
      "net_flow": -957770.7400000021,
      "withdrawal_pressure": 103.56090251287577
    },
    "MP": {
      "group": "CX",
      "deposit_count": 6513.0,
      "deposit_amount": 9152417.88,
      "deposit_difference": 1894663.9400000004,
      "deposit_date": "2026-05-23",
      "deposit_time": "04:00",
      "withdrawal_count": 2266.0,
      "withdrawal_amount": 8270293.19,
      "withdrawal_difference": 2216450.5,
      "withdrawal_date": "2026-05-23",
      "withdrawal_time": "04:00",
      "net_flow": 882124.6900000004,
      "withdrawal_pressure": 90.36183988137569
    },
    "JBG": {
      "group": "CX",
      "deposit_count": 3670.0,
      "deposit_amount": 4570984.0,
      "deposit_difference": 981892.0,
      "deposit_date": "2026-05-23",
      "deposit_time": "04:00",
      "withdrawal_count": 1429.0,
      "withdrawal_amount": 4697063.4,
      "withdrawal_difference": 1058308.3400000003,
      "withdrawal_date": "2026-05-23",
      "withdrawal_time": "04:00",
      "net_flow": -126079.40000000037,
      "withdrawal_pressure": 102.75825511530998
    },
    "DZP": {
      "group": "CX",
      "deposit_count": 4859.0,
      "deposit_amount": 4966875.0,
      "deposit_difference": 1054614.0,
      "deposit_date": "2026-05-23",
      "deposit_time": "04:00",
      "withdrawal_count": 1783.0,
      "withdrawal_amount": 4536099.86,
      "withdrawal_difference": 1192222.3800000004,
      "withdrawal_date": "2026-05-23",
      "withdrawal_time": "04:00",
      "net_flow": 430775.13999999966,
      "withdrawal_pressure": 91.32703883226375
    },
    "SB": {
      "group": "CX",
      "deposit_count": 2720.0,
      "deposit_amount": 3111340.0,
      "deposit_difference": 629028.0,
      "deposit_date": "2026-05-23",
      "deposit_time": "04:00",
      "withdrawal_count": 962.0,
      "withdrawal_amount": 2507309.0,
      "withdrawal_difference": 716405.0,
      "withdrawal_date": "2026-05-23",
      "withdrawal_time": "04:00",
      "net_flow": 604031.0,
      "withdrawal_pressure": 80.58614616210379
    },
    "SLB": {
      "group": "CX",
      "deposit_count": 999.0,
      "deposit_amount": 1101054.0,
      "deposit_difference": 159575.0,
      "deposit_date": "2026-05-23",
      "deposit_time": "04:00",
      "withdrawal_count": 351.0,
      "withdrawal_amount": 1054370.0,
      "withdrawal_difference": 233591.0,
      "withdrawal_date": "2026-05-23",
      "withdrawal_time": "04:00",
      "net_flow": 46684.0,
      "withdrawal_pressure": 95.76006263089731
    },
    "JWAY": {
      "group": "CX",
      "deposit_count": 747.0,
      "deposit_amount": 826674.0,
      "deposit_difference": 184395.0,
      "deposit_date": "2026-05-23",
      "deposit_time": "04:00",
      "withdrawal_count": 281.0,
      "withdrawal_amount": 755128.0,
      "withdrawal_difference": 160561.0,
      "withdrawal_date": "2026-05-23",
      "withdrawal_time": "04:00",
      "net_flow": 71546.0,
      "withdrawal_pressure": 91.34531871088241
    },
    "BJD": {
      "group": "CX",
      "deposit_count": 964.0,
      "deposit_amount": 1738840.0,
      "deposit_difference": 535416.0,
      "deposit_date": "2026-05-23",
      "deposit_time": "04:00",
      "withdrawal_count": 330.0,
      "withdrawal_amount": 1174825.0,
      "withdrawal_difference": 243222.0,
      "withdrawal_date": "2026-05-23",
      "withdrawal_time": "04:00",
      "net_flow": 564015.0,
      "withdrawal_pressure": 67.5637206413471
    },
    "KVP": {
      "group": "CX",
      "deposit_count": 3095.0,
      "deposit_amount": 3495889.1,
      "deposit_difference": 562315.0,
      "deposit_date": "2026-05-23",
      "deposit_time": "04:00",
      "withdrawal_count": 1221.0,
      "withdrawal_amount": 3668503.92,
      "withdrawal_difference": 902667.1799999997,
      "withdrawal_date": "2026-05-23",
      "withdrawal_time": "04:00",
      "net_flow": -172614.81999999983,
      "withdrawal_pressure": 104.93765148328073
    },
    "HBJ": {
      "group": "CX",
      "deposit_count": 4986.0,
      "deposit_amount": 4605592.0,
      "deposit_difference": 865272.0,
      "deposit_date": "2026-05-23",
      "deposit_time": "04:00",
      "withdrawal_count": 1689.0,
      "withdrawal_amount": 4339925.81,
      "withdrawal_difference": 1260255.5899999994,
      "withdrawal_date": "2026-05-23",
      "withdrawal_time": "04:00",
      "net_flow": 265666.1900000004,
      "withdrawal_pressure": 94.23166033812808
    }
  },
  "group_totals": {
    "MCW": {
      "deposit_count": 62567.0,
      "deposit_amount": 80161301.59,
      "deposit_difference": 14802381.909999996,
      "withdrawal_count": 20002.0,
      "withdrawal_amount": 72800589.72,
      "withdrawal_difference": 4023672.3199999994,
      "net_flow": 7360711.870000005,
      "withdrawal_pressure": 90.8176243099847
    },
    "CX": {
      "deposit_count": 76666.0,
      "deposit_amount": 108716133.77999999,
      "deposit_difference": 21196826.73,
      "withdrawal_count": 28896.0,
      "withdrawal_amount": 105036142.35000001,
      "withdrawal_difference": 25757404.509999998,
      "net_flow": 3679991.4299999774,
      "withdrawal_pressure": 96.61504571396287
    }
  },
  "comparison": {
    "m1_vs_cx": {
      "M1": {
        "group": "MCW",
        "deposit_count": 35563.0,
        "deposit_amount": 51761116.94,
        "deposit_difference": 9700722.909999996,
        "deposit_date": "2026-05-23",
        "deposit_time": "04:00",
        "withdrawal_count": 11364.0,
        "withdrawal_amount": 46831061.02,
        "withdrawal_difference": 0.0,
        "withdrawal_date": "2026-05-23",
        "withdrawal_time": "05:00",
        "net_flow": 4930055.919999994,
        "withdrawal_pressure": 90.47536797609145
      },
      "CX": {
        "group": "CX",
        "deposit_count": 30253.0,
        "deposit_amount": 48249614.08,
        "deposit_difference": 9507716.68,
        "deposit_date": "2026-05-23",
        "deposit_time": "04:00",
        "withdrawal_count": 11429.0,
        "withdrawal_amount": 46177999.71,
        "withdrawal_difference": 11272491.649999999,
        "withdrawal_date": "2026-05-23",
        "withdrawal_time": "04:00",
        "net_flow": 2071614.3699999973,
        "withdrawal_pressure": 95.70646437385972
      }
    },
    "mcw_vs_cx_total": {
      "MCW": {
        "deposit_count": 62567.0,
        "deposit_amount": 80161301.59,
        "deposit_difference": 14802381.909999996,
        "withdrawal_count": 20002.0,
        "withdrawal_amount": 72800589.72,
        "withdrawal_difference": 4023672.3199999994,
        "net_flow": 7360711.870000005,
        "withdrawal_pressure": 90.8176243099847
      },
      "CX": {
        "deposit_count": 76666.0,
        "deposit_amount": 108716133.77999999,
        "deposit_difference": 21196826.73,
        "withdrawal_count": 28896.0,
        "withdrawal_amount": 105036142.35000001,
        "withdrawal_difference": 25757404.509999998,
        "net_flow": 3679991.4299999774,
        "withdrawal_pressure": 96.61504571396287
      }
    }
  }
}