{
  "updated_at_utc": "2026-07-20T11:52:44.361817+00:00",
  "source": {
    "deposit_url": "https://stg-risk.mcwchat.com/admin/dashboard-summary-deposit/filter",
    "withdrawal_url": "https://stg-risk.mcwchat.com/admin/dashboard-summary-withdrawal/filter"
  },
  "brands": {
    "M1": {
      "group": "MCW",
      "deposit_count": 101782.0,
      "deposit_amount": 155773375.77,
      "deposit_difference": 8646635.350000024,
      "deposit_date": "2026-07-20",
      "deposit_time": "20:00",
      "withdrawal_count": 35595.0,
      "withdrawal_amount": 159703257.27,
      "withdrawal_difference": 8464917.290000021,
      "withdrawal_date": "2026-07-20",
      "withdrawal_time": "20:00",
      "net_flow": -3929881.5,
      "withdrawal_pressure": 102.52281975695416
    },
    "B1": {
      "group": "MCW",
      "deposit_count": 29983.0,
      "deposit_amount": 36919075.0,
      "deposit_difference": 1853890.0,
      "deposit_date": "2026-07-20",
      "deposit_time": "20:00",
      "withdrawal_count": 11077.0,
      "withdrawal_amount": 36843216.78,
      "withdrawal_difference": 2062096.6499999985,
      "withdrawal_date": "2026-07-20",
      "withdrawal_time": "20:00",
      "net_flow": 75858.21999999881,
      "withdrawal_pressure": 99.79452838403996
    },
    "K1": {
      "group": "MCW",
      "deposit_count": 26682.0,
      "deposit_amount": 29746505.0,
      "deposit_difference": 1335604.0,
      "deposit_date": "2026-07-20",
      "deposit_time": "20:00",
      "withdrawal_count": 8997.0,
      "withdrawal_amount": 29245986.96,
      "withdrawal_difference": 1340766.0,
      "withdrawal_date": "2026-07-20",
      "withdrawal_time": "20:00",
      "net_flow": 500518.0399999991,
      "withdrawal_pressure": 98.31738874869502
    },
    "M2": {
      "group": "MCW",
      "deposit_count": 13138.0,
      "deposit_amount": 21497014.24,
      "deposit_difference": 1057981.0,
      "deposit_date": "2026-07-20",
      "deposit_time": "20:00",
      "withdrawal_count": 5110.0,
      "withdrawal_amount": 23839122.34,
      "withdrawal_difference": 866841.0,
      "withdrawal_date": "2026-07-20",
      "withdrawal_time": "20:00",
      "net_flow": -2342108.1000000015,
      "withdrawal_pressure": 110.8950390684581
    },
    "B2": {
      "group": "MCW",
      "deposit_count": 12316.0,
      "deposit_amount": 20417536.0,
      "deposit_difference": 1015978.0,
      "deposit_date": "2026-07-20",
      "deposit_time": "20:00",
      "withdrawal_count": 5003.0,
      "withdrawal_amount": 20035674.33,
      "withdrawal_difference": 1086820.0,
      "withdrawal_date": "2026-07-20",
      "withdrawal_time": "20:00",
      "net_flow": 381861.6700000018,
      "withdrawal_pressure": 98.12973676157593
    },
    "B4": {
      "group": "MCW",
      "deposit_count": 3506.0,
      "deposit_amount": 3750508.0,
      "deposit_difference": 148278.0,
      "deposit_date": "2026-07-20",
      "deposit_time": "20:00",
      "withdrawal_count": 987.0,
      "withdrawal_amount": 3326337.0,
      "withdrawal_difference": 45921.0,
      "withdrawal_date": "2026-07-20",
      "withdrawal_time": "20:00",
      "net_flow": 424171.0,
      "withdrawal_pressure": 88.69030541995912
    },
    "B3": {
      "group": "MCW",
      "deposit_count": 3180.0,
      "deposit_amount": 4542201.0,
      "deposit_difference": 298331.0,
      "deposit_date": "2026-07-20",
      "deposit_time": "20:00",
      "withdrawal_count": 1133.0,
      "withdrawal_amount": 4368127.0,
      "withdrawal_difference": 81335.0,
      "withdrawal_date": "2026-07-20",
      "withdrawal_time": "20:00",
      "net_flow": 174074.0,
      "withdrawal_pressure": 96.16762886538926
    },
    "TK": {
      "group": "MCW",
      "deposit_count": 2131.0,
      "deposit_amount": 2721412.0,
      "deposit_difference": 106578.0,
      "deposit_date": "2026-07-20",
      "deposit_time": "20:00",
      "withdrawal_count": 760.0,
      "withdrawal_amount": 2886006.0,
      "withdrawal_difference": 120028.0,
      "withdrawal_date": "2026-07-20",
      "withdrawal_time": "20:00",
      "net_flow": -164594.0,
      "withdrawal_pressure": 106.04811031920194
    },
    "B5": {
      "group": "MCW",
      "deposit_count": 2078.0,
      "deposit_amount": 6025544.0,
      "deposit_difference": 186224.0,
      "deposit_date": "2026-07-20",
      "deposit_time": "20:00",
      "withdrawal_count": 1031.0,
      "withdrawal_amount": 6332698.4,
      "withdrawal_difference": 137304.0,
      "withdrawal_date": "2026-07-20",
      "withdrawal_time": "20:00",
      "net_flow": -307154.4000000004,
      "withdrawal_pressure": 105.09753808120894
    },
    "JY": {
      "group": "MCW",
      "deposit_count": 1069.0,
      "deposit_amount": 1138643.0,
      "deposit_difference": 68770.0,
      "deposit_date": "2026-07-20",
      "deposit_time": "20:00",
      "withdrawal_count": 278.0,
      "withdrawal_amount": 1172324.0,
      "withdrawal_difference": 124310.0,
      "withdrawal_date": "2026-07-20",
      "withdrawal_time": "20:00",
      "net_flow": -33681.0,
      "withdrawal_pressure": 102.95799473583907
    },
    "CX": {
      "group": "CX",
      "deposit_count": 85193.0,
      "deposit_amount": 131932670.21,
      "deposit_difference": 6361766.0,
      "deposit_date": "2026-07-20",
      "deposit_time": "20:00",
      "withdrawal_count": 33060.0,
      "withdrawal_amount": 135893298.03,
      "withdrawal_difference": 6760713.450000003,
      "withdrawal_date": "2026-07-20",
      "withdrawal_time": "20:00",
      "net_flow": -3960627.8200000077,
      "withdrawal_pressure": 103.00200686736332
    },
    "MB": {
      "group": "CX",
      "deposit_count": 50036.0,
      "deposit_amount": 78740653.51,
      "deposit_difference": 4030584.0,
      "deposit_date": "2026-07-20",
      "deposit_time": "20:00",
      "withdrawal_count": 19053.0,
      "withdrawal_amount": 76809868.83,
      "withdrawal_difference": 3909770.349999994,
      "withdrawal_date": "2026-07-20",
      "withdrawal_time": "20:00",
      "net_flow": 1930784.6800000072,
      "withdrawal_pressure": 97.54791890347367
    },
    "MP": {
      "group": "CX",
      "deposit_count": 19093.0,
      "deposit_amount": 28104896.05,
      "deposit_difference": 1589717.0,
      "deposit_date": "2026-07-20",
      "deposit_time": "20:00",
      "withdrawal_count": 6775.0,
      "withdrawal_amount": 28883320.83,
      "withdrawal_difference": 1403061.75,
      "withdrawal_date": "2026-07-20",
      "withdrawal_time": "20:00",
      "net_flow": -778424.7799999975,
      "withdrawal_pressure": 102.76971236120262
    },
    "JBG": {
      "group": "CX",
      "deposit_count": 10894.0,
      "deposit_amount": 13738285.42,
      "deposit_difference": 834450.0,
      "deposit_date": "2026-07-20",
      "deposit_time": "20:00",
      "withdrawal_count": 4077.0,
      "withdrawal_amount": 13781694.75,
      "withdrawal_difference": 700505.0,
      "withdrawal_date": "2026-07-20",
      "withdrawal_time": "20:00",
      "net_flow": -43409.330000000075,
      "withdrawal_pressure": 100.3159734178823
    },
    "DZP": {
      "group": "CX",
      "deposit_count": 13907.0,
      "deposit_amount": 14488661.24,
      "deposit_difference": 632536.0,
      "deposit_date": "2026-07-20",
      "deposit_time": "20:00",
      "withdrawal_count": 5127.0,
      "withdrawal_amount": 15548770.41,
      "withdrawal_difference": 630228.0,
      "withdrawal_date": "2026-07-20",
      "withdrawal_time": "20:00",
      "net_flow": -1060109.17,
      "withdrawal_pressure": 107.31681935576816
    },
    "SB": {
      "group": "CX",
      "deposit_count": 8250.0,
      "deposit_amount": 10038248.0,
      "deposit_difference": 456592.0,
      "deposit_date": "2026-07-20",
      "deposit_time": "20:00",
      "withdrawal_count": 3141.0,
      "withdrawal_amount": 10090269.58,
      "withdrawal_difference": 500772.6300000008,
      "withdrawal_date": "2026-07-20",
      "withdrawal_time": "20:00",
      "net_flow": -52021.580000000075,
      "withdrawal_pressure": 100.51823365989763
    },
    "SLB": {
      "group": "CX",
      "deposit_count": 2658.0,
      "deposit_amount": 2872500.85,
      "deposit_difference": 114217.0,
      "deposit_date": "2026-07-20",
      "deposit_time": "20:00",
      "withdrawal_count": 1018.0,
      "withdrawal_amount": 3125173.04,
      "withdrawal_difference": 68422.0,
      "withdrawal_date": "2026-07-20",
      "withdrawal_time": "20:00",
      "net_flow": -252672.18999999994,
      "withdrawal_pressure": 108.79624422043253
    },
    "JWAY": {
      "group": "CX",
      "deposit_count": 2083.0,
      "deposit_amount": 2472583.0,
      "deposit_difference": 130002.0,
      "deposit_date": "2026-07-20",
      "deposit_time": "20:00",
      "withdrawal_count": 813.0,
      "withdrawal_amount": 3105125.0,
      "withdrawal_difference": 188343.0,
      "withdrawal_date": "2026-07-20",
      "withdrawal_time": "20:00",
      "net_flow": -632542.0,
      "withdrawal_pressure": 125.58223525762331
    },
    "BJD": {
      "group": "CX",
      "deposit_count": 2788.0,
      "deposit_amount": 4141381.99,
      "deposit_difference": 263138.0,
      "deposit_date": "2026-07-20",
      "deposit_time": "20:00",
      "withdrawal_count": 1098.0,
      "withdrawal_amount": 4256409.8,
      "withdrawal_difference": 193980.0,
      "withdrawal_date": "2026-07-20",
      "withdrawal_time": "20:00",
      "net_flow": -115027.80999999959,
      "withdrawal_pressure": 102.7775223410386
    },
    "KVP": {
      "group": "CX",
      "deposit_count": 9803.0,
      "deposit_amount": 10605530.45,
      "deposit_difference": 409884.0,
      "deposit_date": "2026-07-20",
      "deposit_time": "20:00",
      "withdrawal_count": 3662.0,
      "withdrawal_amount": 11875547.26,
      "withdrawal_difference": 325915.0,
      "withdrawal_date": "2026-07-20",
      "withdrawal_time": "20:00",
      "net_flow": -1270016.8100000005,
      "withdrawal_pressure": 111.97504279477128
    },
    "HBJ": {
      "group": "CX",
      "deposit_count": 14717.0,
      "deposit_amount": 14418157.24,
      "deposit_difference": 527591.0,
      "deposit_date": "2026-07-20",
      "deposit_time": "20:00",
      "withdrawal_count": 4895.0,
      "withdrawal_amount": 13909270.57,
      "withdrawal_difference": 507760.3900000006,
      "withdrawal_date": "2026-07-20",
      "withdrawal_time": "20:00",
      "net_flow": 508886.6699999999,
      "withdrawal_pressure": 96.47051518769537
    }
  },
  "group_totals": {
    "MCW": {
      "deposit_count": 195865.0,
      "deposit_amount": 282531814.01,
      "deposit_difference": 14718269.350000024,
      "withdrawal_count": 69971.0,
      "withdrawal_amount": 287752750.08,
      "withdrawal_difference": 14330338.94000002,
      "net_flow": -5220936.069999993,
      "withdrawal_pressure": 101.84791085856801
    },
    "CX": {
      "deposit_count": 219422.0,
      "deposit_amount": 311553567.96000004,
      "deposit_difference": 15350477.0,
      "withdrawal_count": 82719.0,
      "withdrawal_amount": 317278748.1,
      "withdrawal_difference": 15189471.569999998,
      "net_flow": -5725180.139999986,
      "withdrawal_pressure": 101.8376230378254
    }
  },
  "comparison": {
    "m1_vs_cx": {
      "M1": {
        "group": "MCW",
        "deposit_count": 101782.0,
        "deposit_amount": 155773375.77,
        "deposit_difference": 8646635.350000024,
        "deposit_date": "2026-07-20",
        "deposit_time": "20:00",
        "withdrawal_count": 35595.0,
        "withdrawal_amount": 159703257.27,
        "withdrawal_difference": 8464917.290000021,
        "withdrawal_date": "2026-07-20",
        "withdrawal_time": "20:00",
        "net_flow": -3929881.5,
        "withdrawal_pressure": 102.52281975695416
      },
      "CX": {
        "group": "CX",
        "deposit_count": 85193.0,
        "deposit_amount": 131932670.21,
        "deposit_difference": 6361766.0,
        "deposit_date": "2026-07-20",
        "deposit_time": "20:00",
        "withdrawal_count": 33060.0,
        "withdrawal_amount": 135893298.03,
        "withdrawal_difference": 6760713.450000003,
        "withdrawal_date": "2026-07-20",
        "withdrawal_time": "20:00",
        "net_flow": -3960627.8200000077,
        "withdrawal_pressure": 103.00200686736332
      }
    },
    "mcw_vs_cx_total": {
      "MCW": {
        "deposit_count": 195865.0,
        "deposit_amount": 282531814.01,
        "deposit_difference": 14718269.350000024,
        "withdrawal_count": 69971.0,
        "withdrawal_amount": 287752750.08,
        "withdrawal_difference": 14330338.94000002,
        "net_flow": -5220936.069999993,
        "withdrawal_pressure": 101.84791085856801
      },
      "CX": {
        "deposit_count": 219422.0,
        "deposit_amount": 311553567.96000004,
        "deposit_difference": 15350477.0,
        "withdrawal_count": 82719.0,
        "withdrawal_amount": 317278748.1,
        "withdrawal_difference": 15189471.569999998,
        "net_flow": -5725180.139999986,
        "withdrawal_pressure": 101.8376230378254
      }
    }
  }
}