{
  "updated_at_utc": "2026-05-05T11:22:18.277493+00:00",
  "source": {
    "deposit_url": "https://stg-risk.mcwchat.com/admin/dashboard-summary-deposit/filter",
    "withdrawal_url": "https://stg-risk.mcwchat.com/admin/dashboard-summary-withdrawal/filter"
  },
  "brands": {
    "M1": {
      "group": "MCW",
      "deposit_count": 84342.0,
      "deposit_amount": 147246594.08,
      "deposit_difference": 4170008.0,
      "deposit_date": "2026-05-05",
      "deposit_time": "20:00",
      "withdrawal_count": 37192.0,
      "withdrawal_amount": 189380013.62,
      "withdrawal_difference": 3710955.0,
      "withdrawal_date": "2026-05-05",
      "withdrawal_time": "20:00",
      "net_flow": -42133419.53999999,
      "withdrawal_pressure": 128.61418955273672
    },
    "B1": {
      "group": "MCW",
      "deposit_count": 21556.0,
      "deposit_amount": 31024919.07,
      "deposit_difference": 932220.0,
      "deposit_date": "2026-05-05",
      "deposit_time": "20:00",
      "withdrawal_count": 9589.0,
      "withdrawal_amount": 33996271.06,
      "withdrawal_difference": 619630.0000000037,
      "withdrawal_date": "2026-05-05",
      "withdrawal_time": "20:00",
      "net_flow": -2971351.990000002,
      "withdrawal_pressure": 109.577307786995
    },
    "K1": {
      "group": "MCW",
      "deposit_count": 18820.0,
      "deposit_amount": 23100176.0,
      "deposit_difference": 669095.0,
      "deposit_date": "2026-05-05",
      "deposit_time": "20:00",
      "withdrawal_count": 7235.0,
      "withdrawal_amount": 24539255.58,
      "withdrawal_difference": 446822.0,
      "withdrawal_date": "2026-05-05",
      "withdrawal_time": "20:00",
      "net_flow": -1439079.5799999982,
      "withdrawal_pressure": 106.2297342669597
    },
    "M2": {
      "group": "MCW",
      "deposit_count": 9730.0,
      "deposit_amount": 18677546.3,
      "deposit_difference": 498810.0,
      "deposit_date": "2026-05-05",
      "deposit_time": "20:00",
      "withdrawal_count": 4391.0,
      "withdrawal_amount": 21117152.12,
      "withdrawal_difference": 511546.0,
      "withdrawal_date": "2026-05-05",
      "withdrawal_time": "20:00",
      "net_flow": -2439605.8200000003,
      "withdrawal_pressure": 113.06170404192761
    },
    "B2": {
      "group": "MCW",
      "deposit_count": 9113.0,
      "deposit_amount": 13316132.0,
      "deposit_difference": 438923.0,
      "deposit_date": "2026-05-05",
      "deposit_time": "20:00",
      "withdrawal_count": 3908.0,
      "withdrawal_amount": 14584744.68,
      "withdrawal_difference": 353706.0,
      "withdrawal_date": "2026-05-05",
      "withdrawal_time": "20:00",
      "net_flow": -1268612.6799999997,
      "withdrawal_pressure": 109.52688573528708
    },
    "B4": {
      "group": "MCW",
      "deposit_count": 2928.0,
      "deposit_amount": 6666130.0,
      "deposit_difference": 184145.0,
      "deposit_date": "2026-05-05",
      "deposit_time": "20:00",
      "withdrawal_count": 1366.0,
      "withdrawal_amount": 7665004.88,
      "withdrawal_difference": 250925.0,
      "withdrawal_date": "2026-05-05",
      "withdrawal_time": "20:00",
      "net_flow": -998874.8799999999,
      "withdrawal_pressure": 114.9843294385198
    },
    "B3": {
      "group": "MCW",
      "deposit_count": 1790.0,
      "deposit_amount": 2802829.0,
      "deposit_difference": 139710.0,
      "deposit_date": "2026-05-05",
      "deposit_time": "20:00",
      "withdrawal_count": 748.0,
      "withdrawal_amount": 2459708.0,
      "withdrawal_difference": 99123.0,
      "withdrawal_date": "2026-05-05",
      "withdrawal_time": "20:00",
      "net_flow": 343121.0,
      "withdrawal_pressure": 87.75804731576561
    },
    "TK": {
      "group": "MCW",
      "deposit_count": 1403.0,
      "deposit_amount": 1682680.0,
      "deposit_difference": 31555.0,
      "deposit_date": "2026-05-05",
      "deposit_time": "20:00",
      "withdrawal_count": 504.0,
      "withdrawal_amount": 1858291.0,
      "withdrawal_difference": 19274.0,
      "withdrawal_date": "2026-05-05",
      "withdrawal_time": "20:00",
      "net_flow": -175611.0,
      "withdrawal_pressure": 110.4363871918606
    },
    "B5": {
      "group": "MCW",
      "deposit_count": 1148.0,
      "deposit_amount": 1057470.54,
      "deposit_difference": 14072.0,
      "deposit_date": "2026-05-05",
      "deposit_time": "20:00",
      "withdrawal_count": 340.0,
      "withdrawal_amount": 1217959.0,
      "withdrawal_difference": 1115.0,
      "withdrawal_date": "2026-05-05",
      "withdrawal_time": "20:00",
      "net_flow": -160488.45999999996,
      "withdrawal_pressure": 115.17663650469166
    },
    "JY": {
      "group": "MCW",
      "deposit_count": 1119.0,
      "deposit_amount": 911835.0,
      "deposit_difference": 19619.0,
      "deposit_date": "2026-05-05",
      "deposit_time": "20:00",
      "withdrawal_count": 308.0,
      "withdrawal_amount": 1382717.25,
      "withdrawal_difference": 6538.0,
      "withdrawal_date": "2026-05-05",
      "withdrawal_time": "20:00",
      "net_flow": -470882.25,
      "withdrawal_pressure": 151.64116863248285
    },
    "CX": {
      "group": "CX",
      "deposit_count": 71595.0,
      "deposit_amount": 126098385.77,
      "deposit_difference": 3332543.0,
      "deposit_date": "2026-05-05",
      "deposit_time": "20:00",
      "withdrawal_count": 34789.0,
      "withdrawal_amount": 158895077.24,
      "withdrawal_difference": 3130188.6100000143,
      "withdrawal_date": "2026-05-05",
      "withdrawal_time": "20:00",
      "net_flow": -32796691.470000014,
      "withdrawal_pressure": 126.00881150835687
    },
    "MB": {
      "group": "CX",
      "deposit_count": 41271.0,
      "deposit_amount": 70906060.74,
      "deposit_difference": 1961023.0,
      "deposit_date": "2026-05-05",
      "deposit_time": "20:00",
      "withdrawal_count": 19434.0,
      "withdrawal_amount": 88583242.79,
      "withdrawal_difference": 1408870.0300000012,
      "withdrawal_date": "2026-05-05",
      "withdrawal_time": "20:00",
      "net_flow": -17677182.050000012,
      "withdrawal_pressure": 124.93042465695439
    },
    "MP": {
      "group": "CX",
      "deposit_count": 14909.0,
      "deposit_amount": 25346965.33,
      "deposit_difference": 635298.0,
      "deposit_date": "2026-05-05",
      "deposit_time": "20:00",
      "withdrawal_count": 6622.0,
      "withdrawal_amount": 31062562.05,
      "withdrawal_difference": 597963.0,
      "withdrawal_date": "2026-05-05",
      "withdrawal_time": "20:00",
      "net_flow": -5715596.7200000025,
      "withdrawal_pressure": 122.54943203490785
    },
    "JBG": {
      "group": "CX",
      "deposit_count": 8065.0,
      "deposit_amount": 10890207.92,
      "deposit_difference": 267002.0,
      "deposit_date": "2026-05-05",
      "deposit_time": "20:00",
      "withdrawal_count": 3611.0,
      "withdrawal_amount": 13180439.49,
      "withdrawal_difference": 275585.0,
      "withdrawal_date": "2026-05-05",
      "withdrawal_time": "20:00",
      "net_flow": -2290231.5700000003,
      "withdrawal_pressure": 121.03019140519771
    },
    "DZP": {
      "group": "CX",
      "deposit_count": 11517.0,
      "deposit_amount": 12400910.32,
      "deposit_difference": 394804.7400000002,
      "deposit_date": "2026-05-05",
      "deposit_time": "20:00",
      "withdrawal_count": 5100.0,
      "withdrawal_amount": 16887454.14,
      "withdrawal_difference": 681553.0,
      "withdrawal_date": "2026-05-05",
      "withdrawal_time": "20:00",
      "net_flow": -4486543.82,
      "withdrawal_pressure": 136.17914898363688
    },
    "SB": {
      "group": "CX",
      "deposit_count": 5793.0,
      "deposit_amount": 6756052.0,
      "deposit_difference": 116009.0,
      "deposit_date": "2026-05-05",
      "deposit_time": "20:00",
      "withdrawal_count": 2542.0,
      "withdrawal_amount": 9268207.03,
      "withdrawal_difference": 813702.5,
      "withdrawal_date": "2026-05-05",
      "withdrawal_time": "20:00",
      "net_flow": -2512155.0299999993,
      "withdrawal_pressure": 137.1837728602444
    },
    "SLB": {
      "group": "CX",
      "deposit_count": 2380.0,
      "deposit_amount": 2353398.19,
      "deposit_difference": 88394.12999999989,
      "deposit_date": "2026-05-05",
      "deposit_time": "20:00",
      "withdrawal_count": 1017.0,
      "withdrawal_amount": 3149331.4,
      "withdrawal_difference": 161643.0,
      "withdrawal_date": "2026-05-05",
      "withdrawal_time": "20:00",
      "net_flow": -795933.21,
      "withdrawal_pressure": 133.82059242596767
    },
    "JWAY": {
      "group": "CX",
      "deposit_count": 1606.0,
      "deposit_amount": 1644090.0,
      "deposit_difference": 21686.0,
      "deposit_date": "2026-05-05",
      "deposit_time": "20:00",
      "withdrawal_count": 657.0,
      "withdrawal_amount": 2325144.79,
      "withdrawal_difference": 28501.0,
      "withdrawal_date": "2026-05-05",
      "withdrawal_time": "20:00",
      "net_flow": -681054.79,
      "withdrawal_pressure": 141.42442262893152
    },
    "BJD": {
      "group": "CX",
      "deposit_count": 2369.0,
      "deposit_amount": 3296434.0,
      "deposit_difference": 126960.0,
      "deposit_date": "2026-05-05",
      "deposit_time": "20:00",
      "withdrawal_count": 1010.0,
      "withdrawal_amount": 3901692.0,
      "withdrawal_difference": 98487.0,
      "withdrawal_date": "2026-05-05",
      "withdrawal_time": "20:00",
      "net_flow": -605258.0,
      "withdrawal_pressure": 118.3609925149419
    },
    "KVP": {
      "group": "CX",
      "deposit_count": 6970.0,
      "deposit_amount": 8296227.48,
      "deposit_difference": 203268.74000000022,
      "deposit_date": "2026-05-05",
      "deposit_time": "20:00",
      "withdrawal_count": 3125.0,
      "withdrawal_amount": 10566023.15,
      "withdrawal_difference": 395382.8300000001,
      "withdrawal_date": "2026-05-05",
      "withdrawal_time": "20:00",
      "net_flow": -2269795.67,
      "withdrawal_pressure": 127.35937117770546
    },
    "HBJ": {
      "group": "CX",
      "deposit_count": 11544.0,
      "deposit_amount": 10763406.0,
      "deposit_difference": 302321.0,
      "deposit_date": "2026-05-05",
      "deposit_time": "20:00",
      "withdrawal_count": 4403.0,
      "withdrawal_amount": 12369158.88,
      "withdrawal_difference": 291396.0700000003,
      "withdrawal_date": "2026-05-05",
      "withdrawal_time": "20:00",
      "net_flow": -1605752.8800000008,
      "withdrawal_pressure": 114.9186315186847
    }
  },
  "group_totals": {
    "MCW": {
      "deposit_count": 151949.0,
      "deposit_amount": 246486311.99,
      "deposit_difference": 7098157.0,
      "withdrawal_count": 65581.0,
      "withdrawal_amount": 298201117.19,
      "withdrawal_difference": 6019634.000000004,
      "net_flow": -51714805.19999999,
      "withdrawal_pressure": 120.98080205041897
    },
    "CX": {
      "deposit_count": 178019.0,
      "deposit_amount": 278752137.74999994,
      "deposit_difference": 7449309.61,
      "withdrawal_count": 82310.0,
      "withdrawal_amount": 350188332.96,
      "withdrawal_difference": 7883272.040000016,
      "net_flow": -71436195.21000004,
      "withdrawal_pressure": 125.62713806846853
    }
  },
  "comparison": {
    "m1_vs_cx": {
      "M1": {
        "group": "MCW",
        "deposit_count": 84342.0,
        "deposit_amount": 147246594.08,
        "deposit_difference": 4170008.0,
        "deposit_date": "2026-05-05",
        "deposit_time": "20:00",
        "withdrawal_count": 37192.0,
        "withdrawal_amount": 189380013.62,
        "withdrawal_difference": 3710955.0,
        "withdrawal_date": "2026-05-05",
        "withdrawal_time": "20:00",
        "net_flow": -42133419.53999999,
        "withdrawal_pressure": 128.61418955273672
      },
      "CX": {
        "group": "CX",
        "deposit_count": 71595.0,
        "deposit_amount": 126098385.77,
        "deposit_difference": 3332543.0,
        "deposit_date": "2026-05-05",
        "deposit_time": "20:00",
        "withdrawal_count": 34789.0,
        "withdrawal_amount": 158895077.24,
        "withdrawal_difference": 3130188.6100000143,
        "withdrawal_date": "2026-05-05",
        "withdrawal_time": "20:00",
        "net_flow": -32796691.470000014,
        "withdrawal_pressure": 126.00881150835687
      }
    },
    "mcw_vs_cx_total": {
      "MCW": {
        "deposit_count": 151949.0,
        "deposit_amount": 246486311.99,
        "deposit_difference": 7098157.0,
        "withdrawal_count": 65581.0,
        "withdrawal_amount": 298201117.19,
        "withdrawal_difference": 6019634.000000004,
        "net_flow": -51714805.19999999,
        "withdrawal_pressure": 120.98080205041897
      },
      "CX": {
        "deposit_count": 178019.0,
        "deposit_amount": 278752137.74999994,
        "deposit_difference": 7449309.61,
        "withdrawal_count": 82310.0,
        "withdrawal_amount": 350188332.96,
        "withdrawal_difference": 7883272.040000016,
        "net_flow": -71436195.21000004,
        "withdrawal_pressure": 125.62713806846853
      }
    }
  }
}