{
  "updated_at_utc": "2026-06-03T23:53:00.958575+00:00",
  "source": {
    "deposit_url": "https://stg-risk.mcwchat.com/admin/dashboard-summary-deposit/filter",
    "withdrawal_url": "https://stg-risk.mcwchat.com/admin/dashboard-summary-withdrawal/filter"
  },
  "brands": {
    "M1": {
      "group": "MCW",
      "deposit_count": 43050.0,
      "deposit_amount": 62990626.96,
      "deposit_difference": 1788671.710000001,
      "deposit_date": "2026-06-04",
      "deposit_time": "08:00",
      "withdrawal_count": 13103.0,
      "withdrawal_amount": 53881564.9,
      "withdrawal_difference": 2990407.0,
      "withdrawal_date": "2026-06-04",
      "withdrawal_time": "08:00",
      "net_flow": 9109062.060000002,
      "withdrawal_pressure": 85.5390198516608
    },
    "B1": {
      "group": "MCW",
      "deposit_count": 11099.0,
      "deposit_amount": 13155227.01,
      "deposit_difference": 418761.0,
      "deposit_date": "2026-06-04",
      "deposit_time": "08:00",
      "withdrawal_count": 3625.0,
      "withdrawal_amount": 11755196.26,
      "withdrawal_difference": 703444.0,
      "withdrawal_date": "2026-06-04",
      "withdrawal_time": "08:00",
      "net_flow": 1400030.75,
      "withdrawal_pressure": 89.35760858451351
    },
    "K1": {
      "group": "MCW",
      "deposit_count": 9623.0,
      "deposit_amount": 9551155.0,
      "deposit_difference": 306659.0,
      "deposit_date": "2026-06-04",
      "deposit_time": "08:00",
      "withdrawal_count": 2982.0,
      "withdrawal_amount": 8214303.24,
      "withdrawal_difference": 331609.0,
      "withdrawal_date": "2026-06-04",
      "withdrawal_time": "08:00",
      "net_flow": 1336851.7599999998,
      "withdrawal_pressure": 86.00324505256171
    },
    "M2": {
      "group": "MCW",
      "deposit_count": 4420.0,
      "deposit_amount": 6885812.0,
      "deposit_difference": 176590.0,
      "deposit_date": "2026-06-04",
      "deposit_time": "08:00",
      "withdrawal_count": 1471.0,
      "withdrawal_amount": 5842131.69,
      "withdrawal_difference": 217851.0,
      "withdrawal_date": "2026-06-04",
      "withdrawal_time": "08:00",
      "net_flow": 1043680.3099999996,
      "withdrawal_pressure": 84.84303216526969
    },
    "B2": {
      "group": "MCW",
      "deposit_count": 4429.0,
      "deposit_amount": 5077423.0,
      "deposit_difference": 120432.0,
      "deposit_date": "2026-06-04",
      "deposit_time": "08:00",
      "withdrawal_count": 1626.0,
      "withdrawal_amount": 6014469.98,
      "withdrawal_difference": 267308.0,
      "withdrawal_date": "2026-06-04",
      "withdrawal_time": "08:00",
      "net_flow": -937046.9800000004,
      "withdrawal_pressure": 118.45516869482809
    },
    "B4": {
      "group": "MCW",
      "deposit_count": 1364.0,
      "deposit_amount": 1880081.0,
      "deposit_difference": 22797.0,
      "deposit_date": "2026-06-04",
      "deposit_time": "08:00",
      "withdrawal_count": 413.0,
      "withdrawal_amount": 1812249.0,
      "withdrawal_difference": 39047.0,
      "withdrawal_date": "2026-06-04",
      "withdrawal_time": "08:00",
      "net_flow": 67832.0,
      "withdrawal_pressure": 96.39207034165017
    },
    "B3": {
      "group": "MCW",
      "deposit_count": 841.0,
      "deposit_amount": 1016468.0,
      "deposit_difference": 22343.0,
      "deposit_date": "2026-06-04",
      "deposit_time": "08:00",
      "withdrawal_count": 273.0,
      "withdrawal_amount": 740572.0,
      "withdrawal_difference": 56717.0,
      "withdrawal_date": "2026-06-04",
      "withdrawal_time": "08:00",
      "net_flow": 275896.0,
      "withdrawal_pressure": 72.85738459056262
    },
    "TK": {
      "group": "MCW",
      "deposit_count": 722.0,
      "deposit_amount": 758601.0,
      "deposit_difference": 8040.0,
      "deposit_date": "2026-06-04",
      "deposit_time": "08:00",
      "withdrawal_count": 257.0,
      "withdrawal_amount": 1073408.0,
      "withdrawal_difference": 63900.0,
      "withdrawal_date": "2026-06-04",
      "withdrawal_time": "08:00",
      "net_flow": -314807.0,
      "withdrawal_pressure": 141.49836343479643
    },
    "B5": {
      "group": "MCW",
      "deposit_count": 470.0,
      "deposit_amount": 463282.0,
      "deposit_difference": 24968.0,
      "deposit_date": "2026-06-04",
      "deposit_time": "08:00",
      "withdrawal_count": 146.0,
      "withdrawal_amount": 481645.0,
      "withdrawal_difference": 27514.0,
      "withdrawal_date": "2026-06-04",
      "withdrawal_time": "08:00",
      "net_flow": -18363.0,
      "withdrawal_pressure": 103.96367655121503
    },
    "JY": {
      "group": "MCW",
      "deposit_count": 376.0,
      "deposit_amount": 367202.0,
      "deposit_difference": 9991.0,
      "deposit_date": "2026-06-04",
      "deposit_time": "08:00",
      "withdrawal_count": 122.0,
      "withdrawal_amount": 360044.0,
      "withdrawal_difference": 1300.0,
      "withdrawal_date": "2026-06-04",
      "withdrawal_time": "08:00",
      "net_flow": 7158.0,
      "withdrawal_pressure": 98.05066421206857
    },
    "CX": {
      "group": "CX",
      "deposit_count": 35198.0,
      "deposit_amount": 60775311.2,
      "deposit_difference": 2070475.3800000027,
      "deposit_date": "2026-06-04",
      "deposit_time": "08:00",
      "withdrawal_count": 13108.0,
      "withdrawal_amount": 54490123.29,
      "withdrawal_difference": 3212866.9499999955,
      "withdrawal_date": "2026-06-04",
      "withdrawal_time": "08:00",
      "net_flow": 6285187.910000004,
      "withdrawal_pressure": 89.6583204826107
    },
    "MB": {
      "group": "CX",
      "deposit_count": 22440.0,
      "deposit_amount": 36110184.29,
      "deposit_difference": 914854.9799999967,
      "deposit_date": "2026-06-04",
      "deposit_time": "08:00",
      "withdrawal_count": 8458.0,
      "withdrawal_amount": 34690715.4,
      "withdrawal_difference": 1336593.6499999985,
      "withdrawal_date": "2026-06-04",
      "withdrawal_time": "08:00",
      "net_flow": 1419468.8900000006,
      "withdrawal_pressure": 96.06906218312186
    },
    "MP": {
      "group": "CX",
      "deposit_count": 8046.0,
      "deposit_amount": 12254822.5,
      "deposit_difference": 416644.0,
      "deposit_date": "2026-06-04",
      "deposit_time": "08:00",
      "withdrawal_count": 3000.0,
      "withdrawal_amount": 13324810.86,
      "withdrawal_difference": 629950.0,
      "withdrawal_date": "2026-06-04",
      "withdrawal_time": "08:00",
      "net_flow": -1069988.3599999994,
      "withdrawal_pressure": 108.731161630452
    },
    "JBG": {
      "group": "CX",
      "deposit_count": 4637.0,
      "deposit_amount": 6239306.38,
      "deposit_difference": 141112.0,
      "deposit_date": "2026-06-04",
      "deposit_time": "08:00",
      "withdrawal_count": 1927.0,
      "withdrawal_amount": 5607045.45,
      "withdrawal_difference": 332743.0,
      "withdrawal_date": "2026-06-04",
      "withdrawal_time": "08:00",
      "net_flow": 632260.9299999997,
      "withdrawal_pressure": 89.8664868898456
    },
    "DZP": {
      "group": "CX",
      "deposit_count": 6016.0,
      "deposit_amount": 6830534.0,
      "deposit_difference": 252470.0,
      "deposit_date": "2026-06-04",
      "deposit_time": "08:00",
      "withdrawal_count": 2352.0,
      "withdrawal_amount": 7050156.22,
      "withdrawal_difference": 405369.0,
      "withdrawal_date": "2026-06-04",
      "withdrawal_time": "08:00",
      "net_flow": -219622.21999999974,
      "withdrawal_pressure": 103.21530088277137
    },
    "SB": {
      "group": "CX",
      "deposit_count": 3444.0,
      "deposit_amount": 4537312.12,
      "deposit_difference": 150672.66000000015,
      "deposit_date": "2026-06-04",
      "deposit_time": "08:00",
      "withdrawal_count": 1515.0,
      "withdrawal_amount": 4658927.64,
      "withdrawal_difference": 272481.0,
      "withdrawal_date": "2026-06-04",
      "withdrawal_time": "08:00",
      "net_flow": -121615.51999999955,
      "withdrawal_pressure": 102.6803428281676
    },
    "SLB": {
      "group": "CX",
      "deposit_count": 1332.0,
      "deposit_amount": 1640665.0,
      "deposit_difference": 38132.0,
      "deposit_date": "2026-06-04",
      "deposit_time": "08:00",
      "withdrawal_count": 629.0,
      "withdrawal_amount": 1733377.0,
      "withdrawal_difference": 86484.0,
      "withdrawal_date": "2026-06-04",
      "withdrawal_time": "08:00",
      "net_flow": -92712.0,
      "withdrawal_pressure": 105.65087936903635
    },
    "JWAY": {
      "group": "CX",
      "deposit_count": 945.0,
      "deposit_amount": 1349721.0,
      "deposit_difference": 25275.0,
      "deposit_date": "2026-06-04",
      "deposit_time": "08:00",
      "withdrawal_count": 431.0,
      "withdrawal_amount": 1627478.0,
      "withdrawal_difference": 89379.0,
      "withdrawal_date": "2026-06-04",
      "withdrawal_time": "08:00",
      "net_flow": -277757.0,
      "withdrawal_pressure": 120.57884555400709
    },
    "BJD": {
      "group": "CX",
      "deposit_count": 1251.0,
      "deposit_amount": 2002189.0,
      "deposit_difference": 161468.0,
      "deposit_date": "2026-06-04",
      "deposit_time": "08:00",
      "withdrawal_count": 532.0,
      "withdrawal_amount": 1889203.41,
      "withdrawal_difference": 135062.0,
      "withdrawal_date": "2026-06-04",
      "withdrawal_time": "08:00",
      "net_flow": 112985.59000000008,
      "withdrawal_pressure": 94.35689687636881
    },
    "KVP": {
      "group": "CX",
      "deposit_count": 4429.0,
      "deposit_amount": 5360234.0,
      "deposit_difference": 220347.0,
      "deposit_date": "2026-06-04",
      "deposit_time": "08:00",
      "withdrawal_count": 1859.0,
      "withdrawal_amount": 5889850.72,
      "withdrawal_difference": 372526.0,
      "withdrawal_date": "2026-06-04",
      "withdrawal_time": "08:00",
      "net_flow": -529616.7199999997,
      "withdrawal_pressure": 109.88047760601496
    },
    "HBJ": {
      "group": "CX",
      "deposit_count": 6124.0,
      "deposit_amount": 6333158.83,
      "deposit_difference": 182158.0,
      "deposit_date": "2026-06-04",
      "deposit_time": "08:00",
      "withdrawal_count": 2214.0,
      "withdrawal_amount": 6529849.37,
      "withdrawal_difference": 399520.60000000056,
      "withdrawal_date": "2026-06-04",
      "withdrawal_time": "08:00",
      "net_flow": -196690.54000000004,
      "withdrawal_pressure": 103.10572567781313
    }
  },
  "group_totals": {
    "MCW": {
      "deposit_count": 76394.0,
      "deposit_amount": 102145877.97,
      "deposit_difference": 2899252.710000001,
      "withdrawal_count": 24018.0,
      "withdrawal_amount": 90175584.07,
      "withdrawal_difference": 4699097.0,
      "net_flow": 11970293.900000006,
      "withdrawal_pressure": 88.28117772553126
    },
    "CX": {
      "deposit_count": 93862.0,
      "deposit_amount": 143433438.32000002,
      "deposit_difference": 4573609.02,
      "withdrawal_count": 36025.0,
      "withdrawal_amount": 137491537.35999998,
      "withdrawal_difference": 7272975.199999995,
      "net_flow": 5941900.960000038,
      "withdrawal_pressure": 95.85738093599649
    }
  },
  "comparison": {
    "m1_vs_cx": {
      "M1": {
        "group": "MCW",
        "deposit_count": 43050.0,
        "deposit_amount": 62990626.96,
        "deposit_difference": 1788671.710000001,
        "deposit_date": "2026-06-04",
        "deposit_time": "08:00",
        "withdrawal_count": 13103.0,
        "withdrawal_amount": 53881564.9,
        "withdrawal_difference": 2990407.0,
        "withdrawal_date": "2026-06-04",
        "withdrawal_time": "08:00",
        "net_flow": 9109062.060000002,
        "withdrawal_pressure": 85.5390198516608
      },
      "CX": {
        "group": "CX",
        "deposit_count": 35198.0,
        "deposit_amount": 60775311.2,
        "deposit_difference": 2070475.3800000027,
        "deposit_date": "2026-06-04",
        "deposit_time": "08:00",
        "withdrawal_count": 13108.0,
        "withdrawal_amount": 54490123.29,
        "withdrawal_difference": 3212866.9499999955,
        "withdrawal_date": "2026-06-04",
        "withdrawal_time": "08:00",
        "net_flow": 6285187.910000004,
        "withdrawal_pressure": 89.6583204826107
      }
    },
    "mcw_vs_cx_total": {
      "MCW": {
        "deposit_count": 76394.0,
        "deposit_amount": 102145877.97,
        "deposit_difference": 2899252.710000001,
        "withdrawal_count": 24018.0,
        "withdrawal_amount": 90175584.07,
        "withdrawal_difference": 4699097.0,
        "net_flow": 11970293.900000006,
        "withdrawal_pressure": 88.28117772553126
      },
      "CX": {
        "deposit_count": 93862.0,
        "deposit_amount": 143433438.32000002,
        "deposit_difference": 4573609.02,
        "withdrawal_count": 36025.0,
        "withdrawal_amount": 137491537.35999998,
        "withdrawal_difference": 7272975.199999995,
        "net_flow": 5941900.960000038,
        "withdrawal_pressure": 95.85738093599649
      }
    }
  }
}