{
  "updated_at_utc": "2026-05-16T13:53:42.371823+00:00",
  "source": {
    "deposit_url": "https://stg-risk.mcwchat.com/admin/dashboard-summary-deposit/filter",
    "withdrawal_url": "https://stg-risk.mcwchat.com/admin/dashboard-summary-withdrawal/filter"
  },
  "brands": {
    "M1": {
      "group": "MCW",
      "deposit_count": 108731.0,
      "deposit_amount": 182635743.24,
      "deposit_difference": 15154031.74000001,
      "deposit_date": "2026-05-16",
      "deposit_time": "22:00",
      "withdrawal_count": 39636.0,
      "withdrawal_amount": 173515495.37,
      "withdrawal_difference": 8028879.469999999,
      "withdrawal_date": "2026-05-16",
      "withdrawal_time": "22:00",
      "net_flow": 9120247.870000005,
      "withdrawal_pressure": 95.00631820025768
    },
    "B1": {
      "group": "MCW",
      "deposit_count": 27196.0,
      "deposit_amount": 35421722.5,
      "deposit_difference": 2868195.0,
      "deposit_date": "2026-05-16",
      "deposit_time": "22:00",
      "withdrawal_count": 10325.0,
      "withdrawal_amount": 33540349.36,
      "withdrawal_difference": 1621042.0,
      "withdrawal_date": "2026-05-16",
      "withdrawal_time": "22:00",
      "net_flow": 1881373.1400000006,
      "withdrawal_pressure": 94.68864581613727
    },
    "K1": {
      "group": "MCW",
      "deposit_count": 23021.0,
      "deposit_amount": 25771907.5,
      "deposit_difference": 2026945.0,
      "deposit_date": "2026-05-16",
      "deposit_time": "22:00",
      "withdrawal_count": 8025.0,
      "withdrawal_amount": 25591497.17,
      "withdrawal_difference": 995397.4600000009,
      "withdrawal_date": "2026-05-16",
      "withdrawal_time": "22:00",
      "net_flow": 180410.3299999982,
      "withdrawal_pressure": 99.2999729259466
    },
    "M2": {
      "group": "MCW",
      "deposit_count": 12468.0,
      "deposit_amount": 21751362.75,
      "deposit_difference": 1962158.0,
      "deposit_date": "2026-05-16",
      "deposit_time": "22:00",
      "withdrawal_count": 4636.0,
      "withdrawal_amount": 20388624.34,
      "withdrawal_difference": 1306802.1099999994,
      "withdrawal_date": "2026-05-16",
      "withdrawal_time": "22:00",
      "net_flow": 1362738.4100000001,
      "withdrawal_pressure": 93.73492858510669
    },
    "B2": {
      "group": "MCW",
      "deposit_count": 11586.0,
      "deposit_amount": 13758719.0,
      "deposit_difference": 1060629.0,
      "deposit_date": "2026-05-16",
      "deposit_time": "22:00",
      "withdrawal_count": 4122.0,
      "withdrawal_amount": 12941516.62,
      "withdrawal_difference": 568018.0,
      "withdrawal_date": "2026-05-16",
      "withdrawal_time": "22:00",
      "net_flow": 817202.3800000008,
      "withdrawal_pressure": 94.06047626962946
    },
    "B4": {
      "group": "MCW",
      "deposit_count": 3539.0,
      "deposit_amount": 5439475.0,
      "deposit_difference": 442020.0,
      "deposit_date": "2026-05-16",
      "deposit_time": "22:00",
      "withdrawal_count": 1317.0,
      "withdrawal_amount": 5757982.85,
      "withdrawal_difference": 305990.0,
      "withdrawal_date": "2026-05-16",
      "withdrawal_time": "22:00",
      "net_flow": -318507.8499999996,
      "withdrawal_pressure": 105.85548881096061
    },
    "B3": {
      "group": "MCW",
      "deposit_count": 2463.0,
      "deposit_amount": 4088488.46,
      "deposit_difference": 352454.0,
      "deposit_date": "2026-05-16",
      "deposit_time": "22:00",
      "withdrawal_count": 857.0,
      "withdrawal_amount": 3320904.61,
      "withdrawal_difference": 156072.0,
      "withdrawal_date": "2026-05-16",
      "withdrawal_time": "22:00",
      "net_flow": 767583.8500000001,
      "withdrawal_pressure": 81.22573030327203
    },
    "TK": {
      "group": "MCW",
      "deposit_count": 1807.0,
      "deposit_amount": 2051665.0,
      "deposit_difference": 180830.0,
      "deposit_date": "2026-05-16",
      "deposit_time": "22:00",
      "withdrawal_count": 565.0,
      "withdrawal_amount": 1885782.0,
      "withdrawal_difference": 39074.0,
      "withdrawal_date": "2026-05-16",
      "withdrawal_time": "22:00",
      "net_flow": 165883.0,
      "withdrawal_pressure": 91.9147131719847
    },
    "B5": {
      "group": "MCW",
      "deposit_count": 1043.0,
      "deposit_amount": 1071408.0,
      "deposit_difference": 39486.0,
      "deposit_date": "2026-05-16",
      "deposit_time": "22:00",
      "withdrawal_count": 296.0,
      "withdrawal_amount": 990482.0,
      "withdrawal_difference": 18859.0,
      "withdrawal_date": "2026-05-16",
      "withdrawal_time": "22:00",
      "net_flow": 80926.0,
      "withdrawal_pressure": 92.44676164449024
    },
    "JY": {
      "group": "MCW",
      "deposit_count": 922.0,
      "deposit_amount": 993816.0,
      "deposit_difference": 74950.0,
      "deposit_date": "2026-05-16",
      "deposit_time": "22:00",
      "withdrawal_count": 306.0,
      "withdrawal_amount": 1031183.0,
      "withdrawal_difference": 35955.0,
      "withdrawal_date": "2026-05-16",
      "withdrawal_time": "22:00",
      "net_flow": -37367.0,
      "withdrawal_pressure": 103.75995154032537
    },
    "CX": {
      "group": "CX",
      "deposit_count": 92931.0,
      "deposit_amount": 166945260.01,
      "deposit_difference": 15303475.75999999,
      "deposit_date": "2026-05-16",
      "deposit_time": "22:00",
      "withdrawal_count": 37258.0,
      "withdrawal_amount": 156860285.7,
      "withdrawal_difference": 8558632.199999988,
      "withdrawal_date": "2026-05-16",
      "withdrawal_time": "22:00",
      "net_flow": 10084974.310000002,
      "withdrawal_pressure": 93.95911311923686
    },
    "MB": {
      "group": "CX",
      "deposit_count": 54539.0,
      "deposit_amount": 94784987.63,
      "deposit_difference": 7855151.899999991,
      "deposit_date": "2026-05-16",
      "deposit_time": "22:00",
      "withdrawal_count": 22541.0,
      "withdrawal_amount": 94179328.21,
      "withdrawal_difference": 3749445.36999999,
      "withdrawal_date": "2026-05-16",
      "withdrawal_time": "22:00",
      "net_flow": 605659.4200000018,
      "withdrawal_pressure": 99.36101756708115
    },
    "MP": {
      "group": "CX",
      "deposit_count": 19044.0,
      "deposit_amount": 30499786.55,
      "deposit_difference": 2674732.0,
      "deposit_date": "2026-05-16",
      "deposit_time": "22:00",
      "withdrawal_count": 7388.0,
      "withdrawal_amount": 31686207.26,
      "withdrawal_difference": 1341496.1400000006,
      "withdrawal_date": "2026-05-16",
      "withdrawal_time": "22:00",
      "net_flow": -1186420.710000001,
      "withdrawal_pressure": 103.88993119035452
    },
    "JBG": {
      "group": "CX",
      "deposit_count": 10926.0,
      "deposit_amount": 14582577.5,
      "deposit_difference": 1174017.0,
      "deposit_date": "2026-05-16",
      "deposit_time": "22:00",
      "withdrawal_count": 4491.0,
      "withdrawal_amount": 14341655.83,
      "withdrawal_difference": 612238.0,
      "withdrawal_date": "2026-05-16",
      "withdrawal_time": "22:00",
      "net_flow": 240921.66999999993,
      "withdrawal_pressure": 98.34788006441248
    },
    "DZP": {
      "group": "CX",
      "deposit_count": 14945.0,
      "deposit_amount": 15974201.92,
      "deposit_difference": 1386730.3900000006,
      "deposit_date": "2026-05-16",
      "deposit_time": "22:00",
      "withdrawal_count": 5794.0,
      "withdrawal_amount": 16622298.68,
      "withdrawal_difference": 568445.0,
      "withdrawal_date": "2026-05-16",
      "withdrawal_time": "22:00",
      "net_flow": -648096.7599999998,
      "withdrawal_pressure": 104.05714641173134
    },
    "SB": {
      "group": "CX",
      "deposit_count": 7481.0,
      "deposit_amount": 8423512.7,
      "deposit_difference": 645385.9999999991,
      "deposit_date": "2026-05-16",
      "deposit_time": "22:00",
      "withdrawal_count": 2941.0,
      "withdrawal_amount": 8523807.16,
      "withdrawal_difference": 335721.0,
      "withdrawal_date": "2026-05-16",
      "withdrawal_time": "22:00",
      "net_flow": -100294.4600000009,
      "withdrawal_pressure": 101.19064888452061
    },
    "SLB": {
      "group": "CX",
      "deposit_count": 2988.0,
      "deposit_amount": 3485306.0,
      "deposit_difference": 210326.0,
      "deposit_date": "2026-05-16",
      "deposit_time": "22:00",
      "withdrawal_count": 1194.0,
      "withdrawal_amount": 3631185.0,
      "withdrawal_difference": 221086.0,
      "withdrawal_date": "2026-05-16",
      "withdrawal_time": "22:00",
      "net_flow": -145879.0,
      "withdrawal_pressure": 104.185543536206
    },
    "JWAY": {
      "group": "CX",
      "deposit_count": 2214.0,
      "deposit_amount": 2553659.0,
      "deposit_difference": 241488.0,
      "deposit_date": "2026-05-16",
      "deposit_time": "22:00",
      "withdrawal_count": 870.0,
      "withdrawal_amount": 2804834.51,
      "withdrawal_difference": 90466.0,
      "withdrawal_date": "2026-05-16",
      "withdrawal_time": "22:00",
      "net_flow": -251175.50999999978,
      "withdrawal_pressure": 109.8359064385652
    },
    "BJD": {
      "group": "CX",
      "deposit_count": 2876.0,
      "deposit_amount": 4090640.0,
      "deposit_difference": 332777.0,
      "deposit_date": "2026-05-16",
      "deposit_time": "22:00",
      "withdrawal_count": 1168.0,
      "withdrawal_amount": 4285401.0,
      "withdrawal_difference": 173935.0,
      "withdrawal_date": "2026-05-16",
      "withdrawal_time": "22:00",
      "net_flow": -194761.0,
      "withdrawal_pressure": 104.76113762149689
    },
    "KVP": {
      "group": "CX",
      "deposit_count": 9401.0,
      "deposit_amount": 10940028.0,
      "deposit_difference": 1026331.0,
      "deposit_date": "2026-05-16",
      "deposit_time": "22:00",
      "withdrawal_count": 3719.0,
      "withdrawal_amount": 11178030.58,
      "withdrawal_difference": 493120.0,
      "withdrawal_date": "2026-05-16",
      "withdrawal_time": "22:00",
      "net_flow": -238002.58000000007,
      "withdrawal_pressure": 102.1755207573509
    },
    "HBJ": {
      "group": "CX",
      "deposit_count": 15060.0,
      "deposit_amount": 14243619.0,
      "deposit_difference": 1192174.0,
      "deposit_date": "2026-05-16",
      "deposit_time": "22:00",
      "withdrawal_count": 5362.0,
      "withdrawal_amount": 14076464.14,
      "withdrawal_difference": 546666.4800000004,
      "withdrawal_date": "2026-05-16",
      "withdrawal_time": "22:00",
      "net_flow": 167154.8599999994,
      "withdrawal_pressure": 98.82645793881457
    }
  },
  "group_totals": {
    "MCW": {
      "deposit_count": 192776.0,
      "deposit_amount": 292984307.45,
      "deposit_difference": 24161698.74000001,
      "withdrawal_count": 70085.0,
      "withdrawal_amount": 278963817.32000005,
      "withdrawal_difference": 13076089.04,
      "net_flow": 14020490.129999936,
      "withdrawal_pressure": 95.21459348726633
    },
    "CX": {
      "deposit_count": 232405.0,
      "deposit_amount": 366523578.31,
      "deposit_difference": 32042589.049999982,
      "withdrawal_count": 92726.0,
      "withdrawal_amount": 358189498.06999993,
      "withdrawal_difference": 16691251.189999979,
      "net_flow": 8334080.240000069,
      "withdrawal_pressure": 97.7261816883848
    }
  },
  "comparison": {
    "m1_vs_cx": {
      "M1": {
        "group": "MCW",
        "deposit_count": 108731.0,
        "deposit_amount": 182635743.24,
        "deposit_difference": 15154031.74000001,
        "deposit_date": "2026-05-16",
        "deposit_time": "22:00",
        "withdrawal_count": 39636.0,
        "withdrawal_amount": 173515495.37,
        "withdrawal_difference": 8028879.469999999,
        "withdrawal_date": "2026-05-16",
        "withdrawal_time": "22:00",
        "net_flow": 9120247.870000005,
        "withdrawal_pressure": 95.00631820025768
      },
      "CX": {
        "group": "CX",
        "deposit_count": 92931.0,
        "deposit_amount": 166945260.01,
        "deposit_difference": 15303475.75999999,
        "deposit_date": "2026-05-16",
        "deposit_time": "22:00",
        "withdrawal_count": 37258.0,
        "withdrawal_amount": 156860285.7,
        "withdrawal_difference": 8558632.199999988,
        "withdrawal_date": "2026-05-16",
        "withdrawal_time": "22:00",
        "net_flow": 10084974.310000002,
        "withdrawal_pressure": 93.95911311923686
      }
    },
    "mcw_vs_cx_total": {
      "MCW": {
        "deposit_count": 192776.0,
        "deposit_amount": 292984307.45,
        "deposit_difference": 24161698.74000001,
        "withdrawal_count": 70085.0,
        "withdrawal_amount": 278963817.32000005,
        "withdrawal_difference": 13076089.04,
        "net_flow": 14020490.129999936,
        "withdrawal_pressure": 95.21459348726633
      },
      "CX": {
        "deposit_count": 232405.0,
        "deposit_amount": 366523578.31,
        "deposit_difference": 32042589.049999982,
        "withdrawal_count": 92726.0,
        "withdrawal_amount": 358189498.06999993,
        "withdrawal_difference": 16691251.189999979,
        "net_flow": 8334080.240000069,
        "withdrawal_pressure": 97.7261816883848
      }
    }
  }
}