{
  "updated_at_utc": "2026-07-17T23:58:15.734003+00:00",
  "source": {
    "deposit_url": "https://stg-risk.mcwchat.com/admin/dashboard-summary-deposit/filter",
    "withdrawal_url": "https://stg-risk.mcwchat.com/admin/dashboard-summary-withdrawal/filter"
  },
  "brands": {
    "M1": {
      "group": "MCW",
      "deposit_count": 48643.0,
      "deposit_amount": 67606315.0,
      "deposit_difference": 2068301.3900000006,
      "deposit_date": "2026-07-18",
      "deposit_time": "08:00",
      "withdrawal_count": 16148.0,
      "withdrawal_amount": 70710907.36,
      "withdrawal_difference": 3372067.0,
      "withdrawal_date": "2026-07-18",
      "withdrawal_time": "08:00",
      "net_flow": -3104592.3599999994,
      "withdrawal_pressure": 104.59216326167164
    },
    "B1": {
      "group": "MCW",
      "deposit_count": 13795.0,
      "deposit_amount": 16197950.0,
      "deposit_difference": 541251.0,
      "deposit_date": "2026-07-18",
      "deposit_time": "08:00",
      "withdrawal_count": 4961.0,
      "withdrawal_amount": 16789152.22,
      "withdrawal_difference": 831439.9999999981,
      "withdrawal_date": "2026-07-18",
      "withdrawal_time": "08:00",
      "net_flow": -591202.2199999988,
      "withdrawal_pressure": 103.649858284536
    },
    "K1": {
      "group": "MCW",
      "deposit_count": 12663.0,
      "deposit_amount": 13549840.25,
      "deposit_difference": 542420.0,
      "deposit_date": "2026-07-18",
      "deposit_time": "08:00",
      "withdrawal_count": 4254.0,
      "withdrawal_amount": 13467613.82,
      "withdrawal_difference": 734647.0,
      "withdrawal_date": "2026-07-18",
      "withdrawal_time": "08:00",
      "net_flow": 82226.4299999997,
      "withdrawal_pressure": 99.3931557237363
    },
    "M2": {
      "group": "MCW",
      "deposit_count": 6080.0,
      "deposit_amount": 9469192.2,
      "deposit_difference": 309667.0,
      "deposit_date": "2026-07-18",
      "deposit_time": "08:00",
      "withdrawal_count": 2233.0,
      "withdrawal_amount": 10225393.21,
      "withdrawal_difference": 529340.0,
      "withdrawal_date": "2026-07-18",
      "withdrawal_time": "08:00",
      "net_flow": -756201.0100000016,
      "withdrawal_pressure": 107.98590834390289
    },
    "B2": {
      "group": "MCW",
      "deposit_count": 6280.0,
      "deposit_amount": 10699453.0,
      "deposit_difference": 544511.0,
      "deposit_date": "2026-07-18",
      "deposit_time": "08:00",
      "withdrawal_count": 2739.0,
      "withdrawal_amount": 11519351.4,
      "withdrawal_difference": 693646.0,
      "withdrawal_date": "2026-07-18",
      "withdrawal_time": "08:00",
      "net_flow": -819898.4000000004,
      "withdrawal_pressure": 107.66299361285105
    },
    "B4": {
      "group": "MCW",
      "deposit_count": 1639.0,
      "deposit_amount": 1633014.0,
      "deposit_difference": 42044.0,
      "deposit_date": "2026-07-18",
      "deposit_time": "08:00",
      "withdrawal_count": 459.0,
      "withdrawal_amount": 1996141.0,
      "withdrawal_difference": 88751.0,
      "withdrawal_date": "2026-07-18",
      "withdrawal_time": "08:00",
      "net_flow": -363127.0,
      "withdrawal_pressure": 122.23661279082727
    },
    "B3": {
      "group": "MCW",
      "deposit_count": 1399.0,
      "deposit_amount": 2263901.0,
      "deposit_difference": 79500.0,
      "deposit_date": "2026-07-18",
      "deposit_time": "08:00",
      "withdrawal_count": 587.0,
      "withdrawal_amount": 2775670.0,
      "withdrawal_difference": 117486.0,
      "withdrawal_date": "2026-07-18",
      "withdrawal_time": "08:00",
      "net_flow": -511769.0,
      "withdrawal_pressure": 122.6056263060973
    },
    "TK": {
      "group": "MCW",
      "deposit_count": 1148.0,
      "deposit_amount": 1214556.0,
      "deposit_difference": 30519.0,
      "deposit_date": "2026-07-18",
      "deposit_time": "08:00",
      "withdrawal_count": 405.0,
      "withdrawal_amount": 1552300.91,
      "withdrawal_difference": 75313.0,
      "withdrawal_date": "2026-07-18",
      "withdrawal_time": "08:00",
      "net_flow": -337744.9099999999,
      "withdrawal_pressure": 127.8080969506552
    },
    "B5": {
      "group": "MCW",
      "deposit_count": 845.0,
      "deposit_amount": 2472793.0,
      "deposit_difference": 81304.0,
      "deposit_date": "2026-07-18",
      "deposit_time": "08:00",
      "withdrawal_count": 441.0,
      "withdrawal_amount": 2744685.42,
      "withdrawal_difference": 152381.0,
      "withdrawal_date": "2026-07-18",
      "withdrawal_time": "08:00",
      "net_flow": -271892.4199999999,
      "withdrawal_pressure": 110.99535707194252
    },
    "JY": {
      "group": "MCW",
      "deposit_count": 465.0,
      "deposit_amount": 437351.0,
      "deposit_difference": 13823.0,
      "deposit_date": "2026-07-18",
      "deposit_time": "08:00",
      "withdrawal_count": 120.0,
      "withdrawal_amount": 379049.0,
      "withdrawal_difference": 33507.0,
      "withdrawal_date": "2026-07-18",
      "withdrawal_time": "08:00",
      "net_flow": 58302.0,
      "withdrawal_pressure": 86.66928851197322
    },
    "CX": {
      "group": "CX",
      "deposit_count": 39250.0,
      "deposit_amount": 57693399.28,
      "deposit_difference": 1789745.0,
      "deposit_date": "2026-07-18",
      "deposit_time": "08:00",
      "withdrawal_count": 15105.0,
      "withdrawal_amount": 63775936.62,
      "withdrawal_difference": 2810110.5,
      "withdrawal_date": "2026-07-18",
      "withdrawal_time": "08:00",
      "net_flow": -6082537.339999996,
      "withdrawal_pressure": 110.54286524265969
    },
    "MB": {
      "group": "CX",
      "deposit_count": 22571.0,
      "deposit_amount": 34050814.9,
      "deposit_difference": 1002268.0,
      "deposit_date": "2026-07-18",
      "deposit_time": "08:00",
      "withdrawal_count": 8734.0,
      "withdrawal_amount": 37295855.88,
      "withdrawal_difference": 1926737.0,
      "withdrawal_date": "2026-07-18",
      "withdrawal_time": "08:00",
      "net_flow": -3245040.980000004,
      "withdrawal_pressure": 109.5299950662855
    },
    "MP": {
      "group": "CX",
      "deposit_count": 8478.0,
      "deposit_amount": 11512710.06,
      "deposit_difference": 524072.7800000012,
      "deposit_date": "2026-07-18",
      "deposit_time": "08:00",
      "withdrawal_count": 2987.0,
      "withdrawal_amount": 12497067.13,
      "withdrawal_difference": 759841.0,
      "withdrawal_date": "2026-07-18",
      "withdrawal_time": "08:00",
      "net_flow": -984357.0700000003,
      "withdrawal_pressure": 108.55017684689265
    },
    "JBG": {
      "group": "CX",
      "deposit_count": 4898.0,
      "deposit_amount": 5468897.75,
      "deposit_difference": 157224.0,
      "deposit_date": "2026-07-18",
      "deposit_time": "08:00",
      "withdrawal_count": 1885.0,
      "withdrawal_amount": 6509609.27,
      "withdrawal_difference": 439324.0,
      "withdrawal_date": "2026-07-18",
      "withdrawal_time": "08:00",
      "net_flow": -1040711.5199999996,
      "withdrawal_pressure": 119.0296393820857
    },
    "DZP": {
      "group": "CX",
      "deposit_count": 6579.0,
      "deposit_amount": 6384025.88,
      "deposit_difference": 194891.0,
      "deposit_date": "2026-07-18",
      "deposit_time": "08:00",
      "withdrawal_count": 2346.0,
      "withdrawal_amount": 6854842.32,
      "withdrawal_difference": 293034.0,
      "withdrawal_date": "2026-07-18",
      "withdrawal_time": "08:00",
      "net_flow": -470816.4400000004,
      "withdrawal_pressure": 107.3749143385365
    },
    "SB": {
      "group": "CX",
      "deposit_count": 3733.0,
      "deposit_amount": 3638690.55,
      "deposit_difference": 161366.0,
      "deposit_date": "2026-07-18",
      "deposit_time": "08:00",
      "withdrawal_count": 1494.0,
      "withdrawal_amount": 5321022.4,
      "withdrawal_difference": 407513.0,
      "withdrawal_date": "2026-07-18",
      "withdrawal_time": "08:00",
      "net_flow": -1682331.8500000006,
      "withdrawal_pressure": 146.23454033484657
    },
    "SLB": {
      "group": "CX",
      "deposit_count": 1400.0,
      "deposit_amount": 1663739.0,
      "deposit_difference": 51965.0,
      "deposit_date": "2026-07-18",
      "deposit_time": "08:00",
      "withdrawal_count": 553.0,
      "withdrawal_amount": 2095622.0,
      "withdrawal_difference": 288055.0,
      "withdrawal_date": "2026-07-18",
      "withdrawal_time": "08:00",
      "net_flow": -431883.0,
      "withdrawal_pressure": 125.95857883958963
    },
    "JWAY": {
      "group": "CX",
      "deposit_count": 987.0,
      "deposit_amount": 1293131.0,
      "deposit_difference": 33679.0,
      "deposit_date": "2026-07-18",
      "deposit_time": "08:00",
      "withdrawal_count": 390.0,
      "withdrawal_amount": 1667285.9,
      "withdrawal_difference": 34670.0,
      "withdrawal_date": "2026-07-18",
      "withdrawal_time": "08:00",
      "net_flow": -374154.8999999999,
      "withdrawal_pressure": 128.93402911228637
    },
    "BJD": {
      "group": "CX",
      "deposit_count": 1339.0,
      "deposit_amount": 1597184.0,
      "deposit_difference": 33738.0,
      "deposit_date": "2026-07-18",
      "deposit_time": "08:00",
      "withdrawal_count": 522.0,
      "withdrawal_amount": 1801958.95,
      "withdrawal_difference": 100933.0,
      "withdrawal_date": "2026-07-18",
      "withdrawal_time": "08:00",
      "net_flow": -204774.94999999995,
      "withdrawal_pressure": 112.82099933382754
    },
    "KVP": {
      "group": "CX",
      "deposit_count": 4645.0,
      "deposit_amount": 4787046.48,
      "deposit_difference": 171120.0,
      "deposit_date": "2026-07-18",
      "deposit_time": "08:00",
      "withdrawal_count": 1581.0,
      "withdrawal_amount": 5400964.97,
      "withdrawal_difference": 358142.0,
      "withdrawal_date": "2026-07-18",
      "withdrawal_time": "08:00",
      "net_flow": -613918.4899999993,
      "withdrawal_pressure": 112.82457758797445
    },
    "HBJ": {
      "group": "CX",
      "deposit_count": 6874.0,
      "deposit_amount": 6711945.0,
      "deposit_difference": 203837.0,
      "deposit_date": "2026-07-18",
      "deposit_time": "08:00",
      "withdrawal_count": 2136.0,
      "withdrawal_amount": 5771702.3,
      "withdrawal_difference": 293398.0,
      "withdrawal_date": "2026-07-18",
      "withdrawal_time": "08:00",
      "net_flow": 940242.7000000002,
      "withdrawal_pressure": 85.99150171820537
    }
  },
  "group_totals": {
    "MCW": {
      "deposit_count": 92957.0,
      "deposit_amount": 125544365.45,
      "deposit_difference": 4253340.390000001,
      "withdrawal_count": 32347.0,
      "withdrawal_amount": 132160264.34000002,
      "withdrawal_difference": 6628577.999999998,
      "net_flow": -6615898.8900000155,
      "withdrawal_pressure": 105.26976966770756
    },
    "CX": {
      "deposit_count": 100754.0,
      "deposit_amount": 134801583.9,
      "deposit_difference": 4323905.780000001,
      "withdrawal_count": 37733.0,
      "withdrawal_amount": 148991867.74,
      "withdrawal_difference": 7711757.5,
      "net_flow": -14190283.840000004,
      "withdrawal_pressure": 110.52679310543323
    }
  },
  "comparison": {
    "m1_vs_cx": {
      "M1": {
        "group": "MCW",
        "deposit_count": 48643.0,
        "deposit_amount": 67606315.0,
        "deposit_difference": 2068301.3900000006,
        "deposit_date": "2026-07-18",
        "deposit_time": "08:00",
        "withdrawal_count": 16148.0,
        "withdrawal_amount": 70710907.36,
        "withdrawal_difference": 3372067.0,
        "withdrawal_date": "2026-07-18",
        "withdrawal_time": "08:00",
        "net_flow": -3104592.3599999994,
        "withdrawal_pressure": 104.59216326167164
      },
      "CX": {
        "group": "CX",
        "deposit_count": 39250.0,
        "deposit_amount": 57693399.28,
        "deposit_difference": 1789745.0,
        "deposit_date": "2026-07-18",
        "deposit_time": "08:00",
        "withdrawal_count": 15105.0,
        "withdrawal_amount": 63775936.62,
        "withdrawal_difference": 2810110.5,
        "withdrawal_date": "2026-07-18",
        "withdrawal_time": "08:00",
        "net_flow": -6082537.339999996,
        "withdrawal_pressure": 110.54286524265969
      }
    },
    "mcw_vs_cx_total": {
      "MCW": {
        "deposit_count": 92957.0,
        "deposit_amount": 125544365.45,
        "deposit_difference": 4253340.390000001,
        "withdrawal_count": 32347.0,
        "withdrawal_amount": 132160264.34000002,
        "withdrawal_difference": 6628577.999999998,
        "net_flow": -6615898.8900000155,
        "withdrawal_pressure": 105.26976966770756
      },
      "CX": {
        "deposit_count": 100754.0,
        "deposit_amount": 134801583.9,
        "deposit_difference": 4323905.780000001,
        "withdrawal_count": 37733.0,
        "withdrawal_amount": 148991867.74,
        "withdrawal_difference": 7711757.5,
        "net_flow": -14190283.840000004,
        "withdrawal_pressure": 110.52679310543323
      }
    }
  }
}